fdk/__init__.py
fdk/constants.py
fdk/context.py
fdk/customer_code.py
fdk/errors.py
fdk/event_handler.py
fdk/fixtures.py
fdk/headers.py
fdk/log.py
fdk/response.py
fdk/runner.py
fdk/version.py
fdk/async_http/__init__.py
fdk/async_http/app.py
fdk/async_http/error_handler.py
fdk/async_http/exceptions.py
fdk/async_http/protocol.py
fdk/async_http/request.py
fdk/async_http/response.py
fdk/async_http/router.py
fdk/async_http/server.py
fdk/scripts/__init__.py
fdk/scripts/fdk.py
fdk/scripts/fdk_tcp_debug.py
fdk/tests/__init__.py
fdk/tests/funcs.py
fdk/tests/tcp_debug.py
fdk/tests/test_delayed_loader.py
fdk/tests/test_headers.py
fdk/tests/test_http_stream.py
fdk/tests/test_protocol.py
fdk/tests/test_tracing.py
fdk-0.1.103.dist-info/LICENSE
fdk-0.1.103.dist-info/METADATA
fdk-0.1.103.dist-info/NOTICE.txt
fdk-0.1.103.dist-info/THIRD_PARTY_LICENSES.txt
fdk-0.1.103.dist-info/WHEEL
fdk-0.1.103.dist-info/entry_points.txt
fdk-0.1.103.dist-info/top_level.txt
fdk-0.1.103.dist-info/RECORD
