Metadata-Version: 2.1
Name: fdk
Version: 0.1.103
Summary: Function Developer Kit for Python
Home-page: https://fnproject.github.io
Author: Denis Makogon
Author-email: denys.makogon@oracle.com
License: Apache License 2.0
Platform: UNKNOWN
Classifier: Intended Audience :: Information Technology
Classifier: Intended Audience :: System Administrators
Classifier: License :: OSI Approved :: Apache Software License
Classifier: Operating System :: POSIX :: Linux
Classifier: Programming Language :: Python
Classifier: Programming Language :: Python :: 3
Classifier: Programming Language :: Python :: 3.11
License-File: LICENSE
License-File: THIRD_PARTY_LICENSES.txt
License-File: NOTICE.txt
Requires-Dist: pbr>=5.11.1
Requires-Dist: iso8601==0.1.12
Requires-Dist: pytest>=5.4.3
Requires-Dist: pytest-asyncio==0.12.0
Requires-Dist: httptools>=0.5.0
Requires-Dist: Cython>=3.0.0
Requires-Dist: wheel>=0.38.1
Requires-Dist: contextvars==2.4; python_version >= "3.7"
